bioDP/__init__.py
bioDP/metabodirect/__init__.py
bioDP/metabodirect/cli.py
bioDP/metabodirect/excel_process.py
bioDP-0.1.4.dist-info/METADATA
bioDP-0.1.4.dist-info/WHEEL
bioDP-0.1.4.dist-info/entry_points.txt
bioDP-0.1.4.dist-info/top_level.txt
bioDP-0.1.4.dist-info/RECORD
