Metadata-Version: 2.2
Name: bioDP
Version: 0.1.4
Summary: pi
Home-page: https://github.com/bit15k/bioDP
Author: bit15k
Author-email: i@logdict.com
Classifier: Intended Audience :: Developers
Classifier: License :: OSI Approved :: MIT License
Classifier: Programming Language :: Python :: 3
Requires-Dist: pandas
Requires-Dist: openpyxl
Dynamic: author
Dynamic: author-email
Dynamic: classifier
Dynamic: description
Dynamic: description-content-type
Dynamic: home-page
Dynamic: requires-dist
Dynamic: summary
